plone.formwidget.recaptcha-2.2.0-py3.7-nspkg.pth
plone/formwidget/recaptcha/__init__.py
plone/formwidget/recaptcha/configure.zcml
plone/formwidget/recaptcha/controlpanel.py
plone/formwidget/recaptcha/interfaces.py
plone/formwidget/recaptcha/meta.zcml
plone/formwidget/recaptcha/norecaptcha.py
plone/formwidget/recaptcha/testing.py
plone/formwidget/recaptcha/upgrades.py
plone/formwidget/recaptcha/validator.py
plone/formwidget/recaptcha/view.py
plone/formwidget/recaptcha/widget.pt
plone/formwidget/recaptcha/widget.py
plone/formwidget/recaptcha/widget_display.pt
plone/formwidget/recaptcha/demo/__init__.py
plone/formwidget/recaptcha/demo/configure.zcml
plone/formwidget/recaptcha/demo/form.py
plone/formwidget/recaptcha/profiles/default/browserlayer.xml
plone/formwidget/recaptcha/profiles/default/controlpanel.xml
plone/formwidget/recaptcha/profiles/default/metadata.xml
plone/formwidget/recaptcha/profiles/default/registry.xml
plone/formwidget/recaptcha/profiles/uninstall/browserlayer.xml
plone/formwidget/recaptcha/profiles/uninstall/controlpanel.xml
plone/formwidget/recaptcha/profiles/uninstall/registry.xml
plone/formwidget/recaptcha/tests/__init__.py
plone/formwidget/recaptcha/tests/test_setup.py
plone.formwidget.recaptcha-2.2.0.dist-info/METADATA
plone.formwidget.recaptcha-2.2.0.dist-info/WHEEL
plone.formwidget.recaptcha-2.2.0.dist-info/entry_points.txt
plone.formwidget.recaptcha-2.2.0.dist-info/namespace_packages.txt
plone.formwidget.recaptcha-2.2.0.dist-info/top_level.txt
plone.formwidget.recaptcha-2.2.0.dist-info/RECORD
