Metadata-Version: 2.1
Name: plone.formwidget.recaptcha
Version: 2.2.0
Summary: ReCaptcha widget for Plone.
Home-page: https://github.com/plone/plone.formwidget.recaptcha
Author: Timo Stollenwerk - Plone Foundation
Author-email: plone-developers@lists.sourceforge.net
License: GPLv2
Keywords: plone discussion plone.app.discussion spam captcha recaptcha
Platform: UNKNOWN
Classifier: Development Status :: 5 - Production/Stable
Classifier: Environment :: Web Environment
Classifier: Framework :: Plone
Classifier: Framework :: Plone :: 4.3
Classifier: Framework :: Plone :: 5.0
Classifier: Framework :: Plone :: 5.1
Classifier: Framework :: Plone :: 5.2
Classifier: License :: OSI Approved :: GNU General Public License v2 (GPLv2)
Classifier: Programming Language :: Python
Classifier: Programming Language :: Python :: 2.7
Classifier: Topic :: Software Development :: Libraries :: Python Modules
Requires-Dist: plone.app.registry
Requires-Dist: plone.registry
Requires-Dist: Products.CMFCore
Requires-Dist: requests
Requires-Dist: setuptools
Requires-Dist: z3c.form
Requires-Dist: zope.annotation
Requires-Dist: zope.component
Requires-Dist: zope.i18nmessageid
Requires-Dist: zope.interface
Requires-Dist: zope.publisher
Requires-Dist: zope.schema
Requires-Dist: Zope2
Provides-Extra: test
Requires-Dist: interlude ; extra == 'test'
Requires-Dist: plone.api ; extra == 'test'
Requires-Dist: plone.app.testing[robot] ; extra == 'test'
Requires-Dist: plone.app.robotframework[debug] ; extra == 'test'
